markmeld/__init__.py
markmeld/_version.py
markmeld/cli.py
markmeld/config_template.yaml
markmeld/const.py
markmeld/deprecated.py
markmeld/exceptions.py
markmeld/glob_factory.py
markmeld/melder.py
markmeld/utilities.py
markmeld-0.3.0.dist-info/LICENSE.txt
markmeld-0.3.0.dist-info/METADATA
markmeld-0.3.0.dist-info/WHEEL
markmeld-0.3.0.dist-info/entry_points.txt
markmeld-0.3.0.dist-info/top_level.txt
markmeld-0.3.0.dist-info/RECORD
