Metadata-Version: 2.1
Name: markmeld
Version: 0.3.0
Summary: Markmeld is a markup melder that combines structured yaml or markdown data into templated markdown output using jinja2.
Home-page: http://markmeld.databio.org
Author: Nathan Sheffield
License: BSD2
Keywords: bioinformatics,sequencing,ngs
Classifier: Development Status :: 4 - Beta
Classifier: License :: OSI Approved :: BSD License
Classifier: Programming Language :: Python :: 3.8
Classifier: Programming Language :: Python :: 3.9
Classifier: Programming Language :: Python :: 3.10
Classifier: Programming Language :: Python :: 3.11
Classifier: Topic :: Scientific/Engineering :: Bio-Informatics
License-File: LICENSE.txt
Requires-Dist: python-frontmatter
Requires-Dist: jinja2 >=3.1
Requires-Dist: logmuse
Requires-Dist: pyyaml
Requires-Dist: requests
Requires-Dist: ubiquerg
